emgdecompy/__init__.py
emgdecompy/contrast.py
emgdecompy/decomposition.py
emgdecompy/preprocessing.py
emgdecompy/viz.py
emgdecompy-0.6.7.dist-info/LICENSE
emgdecompy-0.6.7.dist-info/WHEEL
emgdecompy-0.6.7.dist-info/METADATA
emgdecompy-0.6.7.dist-info/RECORD
