Metadata-Version: 2.1
Name: emgdecompy
Version: 0.6.7
Summary: A package for decomposing multi-channel intramuscular and surface EMG signals into individual motor unit activity based off the blind source algorithm described in Francesco Negro et al 2016 J. Neural Eng. 13 026027.
License: GPL-3.0-only
Author: Daniel King
Requires-Python: >=3.9,<3.11
Classifier: License :: OSI Approved :: GNU General Public License v3 (GPLv3)
Classifier: Programming Language :: Python :: 3
Classifier: Programming Language :: Python :: 3.10
Classifier: Programming Language :: Python :: 3.9
Requires-Dist: altair (>=4.2.0,<5.0.0)
Requires-Dist: altair-data-server (>=0.4.1,<0.5.0)
Requires-Dist: ipywidgets (>=7.7.0,<8.0.0)
Requires-Dist: numpy (>=1.22.3,<2.0.0)
Requires-Dist: pandas (>=1.4.2,<2.0.0)
Requires-Dist: panel (>=0.13.1,<0.14.0)
Requires-Dist: scipy (>=1.8.0,<2.0.0)
Requires-Dist: sklearn (>=0.0,<0.1)
